CHANGELOG.rst
LICENSE.txt
MANIFEST.in
README.rst
setup.py
django_geckoboard/__init__.py
django_geckoboard/decorators.py
django_geckoboard/models.py
django_geckoboard.egg-info/PKG-INFO
django_geckoboard.egg-info/SOURCES.txt
django_geckoboard.egg-info/dependency_links.txt
django_geckoboard.egg-info/requires.txt
django_geckoboard.egg-info/top_level.txt
django_geckoboard/tests/__init__.py
django_geckoboard/tests/settings.py
django_geckoboard/tests/test_decorators.py
django_geckoboard/tests/utils.py