Metadata-Version: 1.1
Name: django-geckoboard
Version: 1.2.7
Summary: Geckoboard custom widgets for Django projects
Home-page: http://github.com/jcassee/django-geckoboard
Author: Joost Cassee
Author-email: joost@cassee.net
License: MIT License
Download-URL: http://github.com/jcassee/django-geckoboard/archives/master
Keywords: django,geckoboard
Platform: any
Classifier: Development Status :: 4 - Beta
Classifier: Environment :: Web Environment
Classifier: Framework :: Django
Classifier: Intended Audience :: Developers
Classifier: License :: OSI Approved :: MIT License
Classifier: Operating System :: OS Independent
Classifier: Programming Language :: Python
Classifier: Topic :: Internet :: WWW/HTTP
Classifier: Topic :: Software Development :: Libraries :: Python Modules
